ideajar/__init__.py
ideajar/main.py
ideajar-1.0.1.dist-info/METADATA
ideajar-1.0.1.dist-info/WHEEL
ideajar-1.0.1.dist-info/entry_points.txt
ideajar-1.0.1.dist-info/licenses/LICENSE
ideajar-1.0.1.dist-info/RECORD
