Metadata-Version: 2.4
Name: ideajar
Version: 1.0.1
Summary: 💡 A simple CLI tool to capture and store your brilliant ideas in a snap
License-File: LICENSE
Keywords: ideas,notes,cli,productivity,brainstorm
Author: ideajar
Author-email: ideajar@example.com
Requires-Python: >=3.8
Classifier: Development Status :: 4 - Beta
Classifier: Environment :: Console
Classifier: Intended Audience :: Developers
Classifier: Intended Audience :: End Users/Desktop
Classifier: License :: OSI Approved :: MIT License
Classifier: Operating System :: OS Independent
Classifier: Programming Language :: Python :: 3
Classifier: Programming Language :: Python :: 3.8
Classifier: Programming Language :: Python :: 3.9
Classifier: Programming Language :: Python :: 3.10
Classifier: Programming Language :: Python :: 3.11
Classifier: Programming Language :: Python :: 3.12
Classifier: Topic :: Utilities
Classifier: Topic :: Text Processing
Provides-Extra: dev
Requires-Dist: pytest (>=7.0.0) ; extra == "dev"
Requires-Dist: pytest-cov (>=4.0.0) ; extra == "dev"
Project-URL: Homepage, https://github.com/ideajar/ideajar
Project-URL: Issues, https://github.com/ideajar/ideajar/issues
Project-URL: Repository, https://github.com/ideajar/ideajar
